for_runners/__init__.py
for_runners/app_settings.py
for_runners/apps.py
for_runners/checks.py
for_runners/constants.py
for_runners/context_processors.py
for_runners/error_handling.py
for_runners/exceptions.py
for_runners/forms.py
for_runners/geo.py
for_runners/gpx.py
for_runners/model_utils.py
for_runners/request_session.py
for_runners/svg.py
for_runners/tasks.py
for_runners/weather.py
for_runners/admin/__init__.py
for_runners/admin/discipline.py
for_runners/admin/distance.py
for_runners/admin/event.py
for_runners/admin/gpx.py
for_runners/admin/gpx_import_export.py
for_runners/admin/utils.py
for_runners/gpx_tools/__init__.py
for_runners/gpx_tools/detect_track_type.py
for_runners/gpx_tools/garmin2gpxpy.py
for_runners/gpx_tools/humanize.py
for_runners/gpx_tools/kml.py
for_runners/gpx_tools/tests/__init__.py
for_runners/gpx_tools/tests/test_detect_track_type.py
for_runners/gpx_tools/tests/test_kml.py
for_runners/management/__init__.py
for_runners/management/commands/__init__.py
for_runners/management/commands/backup.py
for_runners/management/commands/base.py
for_runners/management/commands/fill_basedata.py
for_runners/management/commands/import_tracks.py
for_runners/management/commands/recreate_files.py
for_runners/managers/__init__.py
for_runners/managers/gpx.py
for_runners/migrations/0001_initial.py
for_runners/migrations/0002_auto_20180710_1910.py
for_runners/migrations/0003_auto_20180712_2043.py
for_runners/migrations/0004_auto_20180719_1739.py
for_runners/migrations/0005_auto_20180731_1855.py
for_runners/migrations/0006_auto_20180902_1958.py
for_runners/migrations/0007_auto_20190402_1628.py
for_runners/migrations/0008_auto_20190402_1731.py
for_runners/migrations/0009_auto_20190402_1839.py
for_runners/migrations/0010_participationmodel_person2user.py
for_runners/migrations/0011_participationfilemodel.py
for_runners/migrations/0012_participationimagemodel.py
for_runners/migrations/0013_alter_eventmodel_createby_and_more.py
for_runners/migrations/__init__.py
django_for_runners-0.20.1.dist-info/METADATA
django_for_runners-0.20.1.dist-info/WHEEL
django_for_runners-0.20.1.dist-info/entry_points.txt
django_for_runners-0.20.1.dist-info/licenses/AUTHORS
django_for_runners-0.20.1.dist-info/licenses/LICENSE
django_for_runners-0.20.1.dist-info/RECORD
