Metadata-Version: 2.4
Name: django-for-runners
Version: 0.20.1
Summary: Store your GPX tracks of your running (or other sports activity) in django.
Project-URL: Documentation, https://github.com/jedie/django-for-runners
Project-URL: Source, https://github.com/jedie/django-for-runners
Author-email: Jens Diemer <django-for-runners@jensdiemer.de>
License: GPL-3.0-or-later
License-File: AUTHORS
License-File: LICENSE
Requires-Python: >=3.11
Requires-Dist: autotask
Requires-Dist: bx-django-utils
Requires-Dist: bx-py-utils
Requires-Dist: colorlog
Requires-Dist: django-admin-sortable2
Requires-Dist: django-axes
Requires-Dist: django-dbbackup
Requires-Dist: django-debug-toolbar
Requires-Dist: django-import-export
Requires-Dist: django-processinfo
Requires-Dist: django-tools>=0.56.2
Requires-Dist: django>=5.1
Requires-Dist: geopy
Requires-Dist: gpxpy
Requires-Dist: gunicorn
Requires-Dist: lxml
Requires-Dist: matplotlib
Requires-Dist: requests
Requires-Dist: requests-cache
Requires-Dist: retry-requests
Requires-Dist: svgwrite
